ang/app.py
ang/command_line.py
ang/config.py
ang/models.py
ang/templates.py
ang-0.0.2.dist-info/METADATA
ang-0.0.2.dist-info/WHEEL
ang-0.0.2.dist-info/entry_points.txt
ang-0.0.2.dist-info/top_level.txt
ang-0.0.2.dist-info/RECORD
